gei_bilibilicover_mcp/__init__.py
gei_bilibilicover_mcp-0.1.0.dist-info/WHEEL
gei_bilibilicover_mcp-0.1.0.dist-info/entry_points.txt
gei_bilibilicover_mcp-0.1.0.dist-info/METADATA
gei_bilibilicover_mcp-0.1.0.dist-info/RECORD
